MANIFEST.in
README.md
setup.py
tableview/__init__.py
tableview/core.py
tableview/files.py
tableview.egg-info/PKG-INFO
tableview.egg-info/SOURCES.txt
tableview.egg-info/dependency_links.txt
tableview.egg-info/requires.txt
tableview.egg-info/top_level.txt