Metadata-Version: 1.0
Name: tableview
Version: 0.0.6
Summary: Library for loading and manipulating tabular data.
Home-page: http://www.github.com/ryansturmer/tableview
Author: Ryan Sturmer
Author-email: ryansturmer@gmail.com
License: UNKNOWN
Platform: UNKNOWN
